setup.py
feature_evalution/__init__.py
feature_evalution.egg-info/PKG-INFO
feature_evalution.egg-info/SOURCES.txt
feature_evalution.egg-info/dependency_links.txt
feature_evalution.egg-info/not-zip-safe
feature_evalution.egg-info/top_level.txt