Metadata-Version: 1.0
Name: feature-evalution
Version: 0.5
Summary: feature evalution
Home-page: UNKNOWN
Author: zhaoyang
Author-email: UNKNOWN
License: UNKNOWN
Platform: UNKNOWN
